linpg/CODE_OF_CONDUCT.md
linpg/LICENSE
linpg/README.md
linpg/__init__.py
linpg/abstracts.py
linpg/basic.py
linpg/battle.py
linpg/core.py
linpg/dialogue.py
linpg/exception.py
linpg/interface.py
linpg/py.typed
linpg/ui.py
linpg/__pyinstaller/__init__.py
linpg/__pyinstaller/hook-linpg.py
linpg/config/__init__.py
linpg/config/specifications.json
linpg/config/ui.json
linpg/experimental/__init__.py
linpg/experimental/shadows.py
linpg/language/English.json
linpg/language/SimplifiedChinese.json
linpg/language/TraditionalChinese.json
linpg/language/__init__.py
linpg-3.8.2.dist-info/LICENSE
linpg-3.8.2.dist-info/METADATA
linpg-3.8.2.dist-info/WHEEL
linpg-3.8.2.dist-info/entry_points.txt
linpg-3.8.2.dist-info/top_level.txt
linpg-3.8.2.dist-info/RECORD
