Metadata-Version: 2.1
Name: linpg
Version: 3.8.2
Summary: A game engine based on pygame, which aims to make game development easier.
Author-email: Linpg Foundation <yudong9912@gmail.com>
Project-URL: Bug Tracker, https://github.com/LinpgFoundation/linpg/issues
Project-URL: Homepage, https://github.com/LinpgFoundation/linpg
Classifier: Operating System :: OS Independent
Classifier: Programming Language :: Python :: 3.11
Classifier: Programming Language :: Python :: 3.12
Classifier: Programming Language :: Python :: 3.13
Classifier: Programming Language :: Python :: Implementation :: CPython
Requires-Python: >=3.11
License-File: LICENSE
Requires-Dist: PyYAML
Requires-Dist: av>=12.1.0
Requires-Dist: numpy
Requires-Dist: opencv-python
Requires-Dist: pillow
Requires-Dist: pygame-ce>=2.4.0
Requires-Dist: pyvns>=2.2
